odoo/addons/fieldservice_change_management/README.rst
odoo/addons/fieldservice_change_management/__init__.py
odoo/addons/fieldservice_change_management/__manifest__.py
odoo/addons/fieldservice_change_management/data/change_log_impact.xml
odoo/addons/fieldservice_change_management/data/change_log_stage.xml
odoo/addons/fieldservice_change_management/data/change_log_type.xml
odoo/addons/fieldservice_change_management/data/ir_sequence.xml
odoo/addons/fieldservice_change_management/i18n/es.po
odoo/addons/fieldservice_change_management/i18n/es_AR.po
odoo/addons/fieldservice_change_management/i18n/fieldservice_change_management.pot
odoo/addons/fieldservice_change_management/i18n/it.po
odoo/addons/fieldservice_change_management/i18n/pt_BR.po
odoo/addons/fieldservice_change_management/i18n/pt_PT.po
odoo/addons/fieldservice_change_management/models/__init__.py
odoo/addons/fieldservice_change_management/models/change_log.py
odoo/addons/fieldservice_change_management/models/change_log_impact.py
odoo/addons/fieldservice_change_management/models/change_log_stage.py
odoo/addons/fieldservice_change_management/models/change_log_tags.py
odoo/addons/fieldservice_change_management/models/change_log_type.py
odoo/addons/fieldservice_change_management/models/fsm_location.py
odoo/addons/fieldservice_change_management/readme/CONFIGURE.rst
odoo/addons/fieldservice_change_management/readme/CONTRIBUTORS.rst
odoo/addons/fieldservice_change_management/readme/CREDITS.rst
odoo/addons/fieldservice_change_management/readme/DESCRIPTION.rst
odoo/addons/fieldservice_change_management/readme/INSTALL.rst
odoo/addons/fieldservice_change_management/readme/ROADMAP.rst
odoo/addons/fieldservice_change_management/readme/USAGE.rst
odoo/addons/fieldservice_change_management/report/change_log_reports.xml
odoo/addons/fieldservice_change_management/security/ir.model.access.csv
odoo/addons/fieldservice_change_management/security/security.xml
odoo/addons/fieldservice_change_management/static/description/icon.png
odoo_addon_fieldservice_change_management-15.0.1.0.1.2.dist-info/METADATA
odoo_addon_fieldservice_change_management-15.0.1.0.1.2.dist-info/WHEEL
odoo_addon_fieldservice_change_management-15.0.1.0.1.2.dist-info/top_level.txt
odoo_addon_fieldservice_change_management-15.0.1.0.1.2.dist-info/RECORD
