Metadata-Version: 2.1
Name: odoo-addon-fieldservice_change_management
Version: 15.0.1.0.1.2
Summary: Manage Change Logs on Locations
Home-page: https://github.com/OCA/field-service
Author: Pavlov Media, Odoo Community Association (OCA)
Author-email: support@odoo-community.org
License: AGPL-3
Classifier: Programming Language :: Python
Classifier: Framework :: Odoo
Classifier: Framework :: Odoo :: 15.0
Classifier: License :: OSI Approved :: GNU Affero General Public License v3
Classifier: Development Status :: 4 - Beta
Requires-Python: >=3.8
Requires-Dist: odoo-addon-fieldservice<15.1dev,>=15.0dev
Requires-Dist: odoo<15.1dev,>=15.0a
